cykooz/__init__.py
cykooz/buildout/__init__.py
cykooz/buildout/fixnamespace/__init__.py
cykooz/buildout/fixnamespace/extension.py
cykooz/buildout/fixnamespace/runtests.py
cykooz/buildout/fixnamespace/tests.py
cykooz.buildout.fixnamespace-2.0.6.dist-info/METADATA
cykooz.buildout.fixnamespace-2.0.6.dist-info/WHEEL
cykooz.buildout.fixnamespace-2.0.6.dist-info/entry_points.txt
cykooz.buildout.fixnamespace-2.0.6.dist-info/top_level.txt
cykooz.buildout.fixnamespace-2.0.6.dist-info/RECORD
