Metadata-Version: 2.1
Name: cykooz.buildout.fixnamespace
Version: 2.0.6
Summary: A zc.buildout extension changes value of NAMESPACE_PACKAGE_INIT constant from setuptools
Home-page: https://github.com/Cykooz/cykooz.buildout.fixnamespace
Author: Kirill Kuzminykh
Author-email: cykooz@gmail.com
License: MIT
Keywords: development build
Classifier: Intended Audience :: Developers
Classifier: License :: OSI Approved :: Zope Public License
Classifier: Programming Language :: Python
Classifier: Programming Language :: Python :: 3
Classifier: Programming Language :: Python :: 3.8
Classifier: Programming Language :: Python :: 3.9
Classifier: Programming Language :: Python :: 3.10
Classifier: Programming Language :: Python :: 3.11
Classifier: Framework :: Buildout
Classifier: Topic :: Software Development :: Libraries :: Python Modules
Requires-Dist: setuptools
Requires-Dist: zc.buildout
Provides-Extra: test
Requires-Dist: pytest ; extra == 'test'
Requires-Dist: zc.buildout[test] ; extra == 'test'
